su6_plugin_svelte_check/__about__.py
su6_plugin_svelte_check/__init__.py
su6_plugin_svelte_check/cli.py
su6_plugin_svelte_check/helpers.py
su6_plugin_svelte_check-0.5.1.dist-info/METADATA
su6_plugin_svelte_check-0.5.1.dist-info/WHEEL
su6_plugin_svelte_check-0.5.1.dist-info/entry_points.txt
su6_plugin_svelte_check-0.5.1.dist-info/licenses/LICENSE.txt
su6_plugin_svelte_check-0.5.1.dist-info/RECORD
